{"LST": {"anomalies": {"parameter": "LST", "city": "ahmedabad", "anomalies": [{"date": "2026-01-25", "lat": 22.91, "lng": 72.41, "value": 21.132, "severity": "high", "anomaly_score": -0.1534, "deviation": 2.0, "direction": "below", "description": "Unusual cold event \u2014 surface temperature dropped well below expected range. May indicate weather anomaly or sensor calibration event.", "parameter": "LST"}, {"date": "2020-05-16", "lat": 23.2, "lng": 72.4, "value": 46.1237, "severity": "moderate", "anomaly_score": -0.1429, "deviation": 2.32, "direction": "above", "description": "Above-normal surface temperature detected. Mild heat stress \u2014 monitor for sustained trends.", "parameter": "LST"}, {"date": "2026-01-01", "lat": 23.19, "lng": 72.69, "value": 21.2572, "severity": "moderate", "anomaly_score": -0.134, "deviation": 1.98, "direction": "below", "description": "Below-normal surface temperature. Unusual for this period \u2014 possible weather system influence.", "parameter": "LST"}, {"date": "2026-01-17", "lat": 22.91, "lng": 72.41, "value": 21.9578, "severity": "moderate", "anomaly_score": -0.1193, "deviation": 1.86, "direction": "below", "description": "Below-normal surface temperature. Unusual for this period \u2014 possible weather system influence.", "parameter": "LST"}, {"date": "2026-01-09", "lat": 22.91, "lng": 72.41, "value": 22.4761, "severity": "moderate", "anomaly_score": -0.1081, "deviation": 1.77, "direction": "below", "description": "Below-normal surface temperature. Unusual for this period \u2014 possible weather system influence.", "parameter": "LST"}, {"date": "2020-05-24", "lat": 22.91, "lng": 72.41, "value": 45.8262, "severity": "moderate", "anomaly_score": -0.0952, "deviation": 2.27, "direction": "above", "description": "Above-normal surface temperature detected. Mild heat stress \u2014 monitor for sustained trends.", "parameter": "LST"}, {"date": "2023-05-09", "lat": 22.91, "lng": 72.55, "value": 45.5488, "severity": "moderate", "anomaly_score": -0.079, "deviation": 2.22, "direction": "above", "description": "Above-normal surface temperature detected. Mild heat stress \u2014 monitor for sustained trends.", "parameter": "LST"}, {"date": "2020-04-30", "lat": 23.2, "lng": 72.4, "value": 45.061, "severity": "moderate", "anomaly_score": -0.0769, "deviation": 2.14, "direction": "above", "description": "Above-normal surface temperature detected. Mild heat stress \u2014 monitor for sustained trends.", "parameter": "LST"}, {"date": "2025-12-27", "lat": 23.19, "lng": 72.69, "value": 23.1209, "severity": "moderate", "anomaly_score": -0.0687, "deviation": 1.66, "direction": "below", "description": "Below-normal surface temperature. Unusual for this period \u2014 possible weather system influence.", "parameter": "LST"}, {"date": "2021-05-01", "lat": 23.2, "lng": 72.4, "value": 44.1693, "severity": "moderate", "anomaly_score": -0.0598, "deviation": 1.98, "direction": "above", "description": "Above-normal surface temperature detected. Mild heat stress \u2014 monitor for sustained trends.", "parameter": "LST"}, {"date": "2025-01-09", "lat": 23.19, "lng": 72.69, "value": 23.431, "severity": "moderate", "anomaly_score": -0.0558, "deviation": 1.6, "direction": "below", "description": "Below-normal surface temperature. Unusual for this period \u2014 possible weather system influence.", "parameter": "LST"}, {"date": "2020-05-08", "lat": 23.2, "lng": 72.4, "value": 45.2666, "severity": "moderate", "anomaly_score": -0.0532, "deviation": 2.17, "direction": "above", "description": "Above-normal surface temperature detected. Mild heat stress \u2014 monitor for sustained trends.", "parameter": "LST"}, {"date": "2022-04-23", "lat": 23.2, "lng": 72.4, "value": 45.1623, "severity": "moderate", "anomaly_score": -0.0529, "deviation": 2.16, "direction": "above", "description": "Above-normal surface temperature detected. Mild heat stress \u2014 monitor for sustained trends.", "parameter": "LST"}, {"date": "2024-12-26", "lat": 23.08, "lng": 72.7, "value": 23.8389, "severity": "moderate", "anomaly_score": -0.0404, "deviation": 1.53, "direction": "below", "description": "Below-normal surface temperature. Unusual for this period \u2014 possible weather system influence.", "parameter": "LST"}, {"date": "2021-05-09", "lat": 23.2, "lng": 72.4, "value": 44.0126, "severity": "moderate", "anomaly_score": -0.0398, "deviation": 1.96, "direction": "above", "description": "Above-normal surface temperature detected. Mild heat stress \u2014 monitor for sustained trends.", "parameter": "LST"}, {"date": "2020-04-14", "lat": 23.05, "lng": 72.69, "value": 43.1848, "severity": "moderate", "anomaly_score": -0.0192, "deviation": 1.81, "direction": "above", "description": "Above-normal surface temperature detected. Mild heat stress \u2014 monitor for sustained trends.", "parameter": "LST"}, {"date": "2023-05-17", "lat": 22.91, "lng": 72.55, "value": 43.6615, "severity": "moderate", "anomaly_score": -0.0142, "deviation": 1.9, "direction": "above", "description": "Above-normal surface temperature detected. Mild heat stress \u2014 monitor for sustained trends.", "parameter": "LST"}, {"date": "2020-04-22", "lat": 23.2, "lng": 72.4, "value": 43.7234, "severity": "moderate", "anomaly_score": -0.0132, "deviation": 1.91, "direction": "above", "description": "Above-normal surface temperature detected. Mild heat stress \u2014 monitor for sustained trends.", "parameter": "LST"}, {"date": "2024-04-30", "lat": 22.91, "lng": 72.55, "value": 42.9487, "severity": "moderate", "anomaly_score": -0.0076, "deviation": 1.77, "direction": "above", "description": "Above-normal surface temperature detected. Mild heat stress \u2014 monitor for sustained trends.", "parameter": "LST"}, {"date": "2021-04-15", "lat": 23.05, "lng": 72.69, "value": 42.7049, "severity": "moderate", "anomaly_score": -0.0074, "deviation": 1.73, "direction": "above", "description": "Above-normal surface temperature detected. Mild heat stress \u2014 monitor for sustained trends.", "parameter": "LST"}], "total_points": 225658, "dates_analyzed": 244, "anomaly_count": 20, "contamination": 0.08}, "trends": {"parameter": "LST", "city": "ahmedabad", "historical": {"2020-01-01": 26.9665, "2020-01-09": 24.2162, "2020-01-17": 26.5063, "2020-01-25": 27.6073, "2020-02-02": 27.4538, "2020-02-10": 30.7791, "2020-02-18": 32.1337, "2020-02-26": 33.1344, "2020-03-05": 31.9453, "2020-03-13": 35.0625, "2020-03-21": 36.6949, "2020-03-29": 40.8276, "2020-04-06": 41.5024, "2020-04-14": 43.1848, "2020-04-22": 43.7234, "2020-04-30": 45.061, "2020-05-08": 45.2666, "2020-05-16": 46.1237, "2020-05-24": 45.8262, "2020-06-01": 41.1143, "2020-06-09": 34.1868, "2020-06-17": 34.8082, "2020-06-25": 39.2529, "2020-07-03": 29.67, "2020-08-04": 29.511, "2020-08-20": 28.5358, "2020-08-28": 32.7016, "2020-09-05": 29.9826, "2020-09-21": 32.9395, "2020-09-29": 34.0559, "2020-10-07": 35.2795, "2020-10-15": 36.5789, "2020-10-23": 37.0018, "2020-10-31": 34.5622, "2020-11-08": 33.001, "2020-11-16": 32.9996, "2020-11-24": 32.0645, "2020-12-02": 33.0804, "2020-12-10": 29.0146, "2020-12-18": 27.6654, "2020-12-26": 26.141, "2021-01-01": 26.2553, "2021-01-09": 27.615, "2021-01-17": 28.5439, "2021-01-25": 26.4706, "2021-02-02": 28.3601, "2021-02-10": 30.11, "2021-02-18": 33.2597, "2021-02-26": 35.7828, "2021-03-06": 37.0715, "2021-03-14": 35.6407, "2021-03-22": 39.5773, "2021-03-30": 40.5775, "2021-04-07": 41.9523, "2021-04-15": 42.7049, "2021-04-23": 42.0596, "2021-05-01": 44.1693, "2021-05-09": 44.0126, "2021-05-17": 34.2022, "2021-05-25": 37.6333, "2021-06-02": 35.5285, "2021-06-10": 35.1621, "2021-06-26": 32.4918, "2021-07-04": 37.7211, "2021-08-13": 29.09, "2021-08-21": 32.8915, "2021-08-29": 35.8167, "2021-09-22": 28.7388, "2021-09-30": 31.5524, "2021-10-08": 32.6345, "2021-10-16": 33.069, "2021-10-24": 33.1315, "2021-11-01": 33.3199, "2021-11-09": 31.8061, "2021-11-17": 32.915, "2021-11-25": 32.6205, "2021-12-03": 29.0222, "2021-12-11": 28.4827, "2021-12-19": 28.1956, "2021-12-27": 24.6905, "2022-01-01": 27.2873, "2022-01-09": 24.6969, "2022-01-17": 26.8259, "2022-01-25": 27.3745, "2022-02-02": 28.4861, "2022-02-10": 30.4366, "2022-02-18": 32.8854, "2022-02-26": 34.0478, "2022-03-06": 36.2867, "2022-03-14": 39.0784, "2022-03-22": 39.7027, "2022-03-30": 41.5245, "2022-04-07": 42.0839, "2022-04-15": 42.446, "2022-04-23": 45.1623, "2022-05-01": 42.2845, "2022-05-09": 42.0545, "2022-05-17": 41.6732, "2022-05-25": 39.8063, "2022-06-02": 40.8948, "2022-06-10": 41.5157, "2022-06-18": 38.4564, "2022-06-26": 42.45, "2022-08-21": 28.1275, "2022-08-29": 30.201, "2022-09-06": 34.7136, "2022-09-14": 29.9886, "2022-09-22": 30.8039, "2022-09-30": 32.9324, "2022-10-24": 33.9496, "2022-11-01": 34.002, "2022-11-09": 32.2229, "2022-11-17": 31.8283, "2022-11-25": 30.3263, "2022-12-03": 29.2188, "2022-12-11": 30.6128, "2022-12-19": 28.9355, "2022-12-27": 27.4556, "2023-01-01": 25.3472, "2023-01-09": 25.7319, "2023-01-17": 25.3254, "2023-01-25": 25.2123, "2023-02-02": 29.6136, "2023-02-10": 31.7715, "2023-02-18": 33.231, "2023-02-26": 34.2352, "2023-03-06": 34.3769, "2023-03-14": 33.7414, "2023-03-22": 35.221, "2023-03-30": 36.9969, "2023-04-07": 40.2056, "2023-04-15": 41.8433, "2023-04-23": 40.7829, "2023-05-01": 39.8839, "2023-05-09": 45.5488, "2023-05-17": 43.6615, "2023-05-25": 39.1271, "2023-06-02": 36.9299, "2023-06-10": 36.0501, "2023-06-18": 36.99, "2023-06-26": 31.6734, "2023-08-13": 34.19, "2023-08-21": 30.8922, "2023-08-29": 32.871, "2023-09-22": 31.9642, "2023-09-30": 31.9758, "2023-10-08": 33.3529, "2023-10-16": 33.875, "2023-10-24": 33.8125, "2023-11-01": 32.9822, "2023-11-09": 32.5023, "2023-11-17": 30.5911, "2023-11-25": 25.9664, "2023-12-03": 27.8981, "2023-12-11": 27.4789, "2023-12-19": 26.5164, "2023-12-27": 26.549, "2024-01-01": 24.4603, "2024-01-09": 26.5569, "2024-01-17": 24.2464, "2024-01-25": 25.8792, "2024-02-02": 28.3189, "2024-02-10": 28.7442, "2024-02-18": 31.0028, "2024-02-26": 30.0989, "2024-03-05": 33.0735, "2024-03-13": 34.4788, "2024-03-21": 36.871, "2024-03-29": 36.2979, "2024-04-06": 38.1264, "2024-04-14": 40.5959, "2024-04-22": 41.1045, "2024-04-30": 42.9487, "2024-05-08": 40.7003, "2024-05-16": 40.2759, "2024-05-24": 38.8979, "2024-06-01": 40.1546, "2024-06-09": 39.4835, "2024-06-17": 40.4623, "2024-07-11": 30.1276, "2024-08-12": 31.1923, "2024-08-28": 26.9568, "2024-09-05": 27.9699, "2024-09-13": 29.1777, "2024-09-29": 30.1367, "2024-10-07": 31.8506, "2024-10-15": 30.5546, "2024-10-23": 32.9079, "2024-10-31": 33.0359, "2024-11-08": 31.6106, "2024-11-16": 28.9386, "2024-11-24": 27.6411, "2024-12-02": 26.8788, "2024-12-10": 24.6286, "2024-12-18": 24.7968, "2024-12-26": 23.8389, "2025-01-01": 24.6865, "2025-01-09": 23.431, "2025-01-17": 25.9474, "2025-01-25": 25.79, "2025-02-02": 26.0722, "2025-02-10": 28.611, "2025-02-18": 29.1746, "2025-02-26": 30.147, "2025-03-06": 34.5013, "2025-03-14": 34.9497, "2025-03-22": 34.9189, "2025-03-30": 37.1603, "2025-04-07": 37.5122, "2025-04-15": 37.9636, "2025-04-23": 39.4181, "2025-05-01": 39.6789, "2025-05-09": 35.5277, "2025-05-17": 35.5653, "2025-05-25": 28.8378, "2025-06-02": 33.9944, "2025-06-10": 34.336, "2025-07-04": 26.99, "2025-07-28": 26.61, "2025-08-05": 26.908, "2025-08-29": 27.9862, "2025-09-06": 27.8734, "2025-09-14": 29.2841, "2025-09-22": 29.9276, "2025-09-30": 27.234, "2025-10-08": 28.9554, "2025-10-24": 30.9291, "2025-11-01": 26.4231, "2025-11-09": 26.0924, "2025-11-17": 25.5026, "2025-11-25": 26.3351, "2025-12-03": 24.8802, "2025-12-11": 24.8088, "2025-12-19": 24.4852, "2025-12-27": 23.1209, "2026-01-01": 21.2572, "2026-01-09": 22.4761, "2026-01-17": 21.9578, "2026-01-25": 21.132, "2026-02-02": 25.1817, "2026-02-10": 26.1317, "2026-02-18": 28.3156, "2026-02-26": 29.98, "2026-03-06": 32.4025}, "forecast": {"2026-03-07": 32.4534, "2026-03-08": 33.0093, "2026-03-09": 33.2495, "2026-03-10": 33.4712, "2026-03-11": 33.6155, "2026-03-12": 33.7239, "2026-03-13": 33.8005, "2026-03-14": 33.8559, "2026-03-15": 33.8957, "2026-03-16": 33.9243, "2026-03-17": 33.9448, "2026-03-18": 33.9596, "2026-03-19": 33.9703, "2026-03-20": 33.9779, "2026-03-21": 33.9834, "2026-03-22": 33.9874, "2026-03-23": 33.9902, "2026-03-24": 33.9922, "2026-03-25": 33.9937, "2026-03-26": 33.9948, "2026-03-27": 33.9955, "2026-03-28": 33.9961, "2026-03-29": 33.9965, "2026-03-30": 33.9967, "2026-03-31": 33.9969, "2026-04-01": 33.9971, "2026-04-02": 33.9972, "2026-04-03": 33.9973, "2026-04-04": 33.9973, "2026-04-05": 33.9974}, "trend_direction": "increasing", "model": "ARIMA(2,1,1)", "forecast_days": 30}, "hotspots": {"parameter": "LST", "city": "ahmedabad", "hotspots": [{"cluster_id": 0, "center_lat": 23.0547, "center_lng": 72.5533, "avg_value": 40.9995, "num_points": 56415, "severity": "critical", "parameter": "LST", "radius_km": 2.2}], "total_points": 225658, "hot_points": 56415, "cluster_count": 1, "threshold": 36.8729}}, "NDVI": {"anomalies": {"parameter": "NDVI", "city": "ahmedabad", "anomalies": [{"date": "2024-07-27", "lat": 23.05, "lng": 72.55, "value": 0.0895, "severity": "high", "anomaly_score": -0.2085, "deviation": 3.09, "direction": "below", "description": "Severe vegetation loss \u2014 NDVI dropped sharply. Possible deforestation, fire damage, or drought stress event.", "parameter": "NDVI"}, {"date": "2023-07-28", "lat": 23.05, "lng": 72.55, "value": 0.1137, "severity": "high", "anomaly_score": -0.1783, "deviation": 2.83, "direction": "below", "description": "Severe vegetation loss \u2014 NDVI dropped sharply. Possible deforestation, fire damage, or drought stress event.", "parameter": "NDVI"}, {"date": "2020-09-13", "lat": 22.91, "lng": 72.55, "value": 0.6225, "severity": "high", "anomaly_score": -0.1537, "deviation": 2.52, "direction": "above", "description": "Sudden vegetation surge \u2014 NDVI spiked above normal. Likely post-monsoon rapid growth or irrigation activity.", "parameter": "NDVI"}, {"date": "2022-07-12", "lat": 22.91, "lng": 72.41, "value": 0.1802, "severity": "moderate", "anomaly_score": -0.0902, "deviation": 2.13, "direction": "below", "description": "Mild vegetation decline detected. Early indicator of stress \u2014 recommend monitoring.", "parameter": "NDVI"}, {"date": "2021-09-30", "lat": 23.2, "lng": 72.69, "value": 0.6024, "severity": "moderate", "anomaly_score": -0.0844, "deviation": 2.31, "direction": "above", "description": "Slightly elevated vegetation index. Green cover above seasonal baseline.", "parameter": "NDVI"}, {"date": "2021-07-28", "lat": 23.05, "lng": 72.41, "value": 0.2077, "severity": "moderate", "anomaly_score": -0.0741, "deviation": 1.84, "direction": "below", "description": "Mild vegetation decline detected. Early indicator of stress \u2014 recommend monitoring.", "parameter": "NDVI"}, {"date": "2025-08-13", "lat": 23.05, "lng": 72.69, "value": 0.189, "severity": "moderate", "anomaly_score": -0.0724, "deviation": 2.04, "direction": "below", "description": "Mild vegetation decline detected. Early indicator of stress \u2014 recommend monitoring.", "parameter": "NDVI"}, {"date": "2025-06-26", "lat": 23.05, "lng": 72.55, "value": 0.2351, "severity": "moderate", "anomaly_score": -0.0431, "deviation": 1.55, "direction": "below", "description": "Mild vegetation decline detected. Early indicator of stress \u2014 recommend monitoring.", "parameter": "NDVI"}, {"date": "2025-09-14", "lat": 22.91, "lng": 72.41, "value": 0.5931, "severity": "moderate", "anomaly_score": -0.0223, "deviation": 2.21, "direction": "above", "description": "Slightly elevated vegetation index. Green cover above seasonal baseline.", "parameter": "NDVI"}, {"date": "2022-06-26", "lat": 23.05, "lng": 72.55, "value": 0.2453, "severity": "moderate", "anomaly_score": -0.0094, "deviation": 1.45, "direction": "below", "description": "Mild vegetation decline detected. Early indicator of stress \u2014 recommend monitoring.", "parameter": "NDVI"}, {"date": "2020-09-29", "lat": 23.04, "lng": 72.4, "value": 0.5431, "severity": "moderate", "anomaly_score": -0.0089, "deviation": 1.69, "direction": "above", "description": "Slightly elevated vegetation index. Green cover above seasonal baseline.", "parameter": "NDVI"}, {"date": "2023-08-29", "lat": 22.91, "lng": 72.69, "value": 0.5087, "severity": "moderate", "anomaly_score": -0.0006, "deviation": 1.32, "direction": "above", "description": "Slightly elevated vegetation index. Green cover above seasonal baseline.", "parameter": "NDVI"}], "total_points": 136462, "dates_analyzed": 142, "anomaly_count": 12, "contamination": 0.08}, "trends": {"parameter": "NDVI", "city": "ahmedabad", "historical": {"2020-01-01": 0.386, "2020-01-17": 0.3905, "2020-02-02": 0.3742, "2020-02-18": 0.3684, "2020-03-05": 0.3837, "2020-03-21": 0.3813, "2020-04-06": 0.3398, "2020-04-22": 0.3281, "2020-05-08": 0.3092, "2020-05-24": 0.2728, "2020-06-09": 0.3656, "2020-06-25": 0.38, "2020-07-11": 0.4564, "2020-07-27": 0.416, "2020-08-12": 0.2937, "2020-08-28": 0.5851, "2020-09-13": 0.6225, "2020-09-29": 0.5431, "2020-10-15": 0.4492, "2020-10-31": 0.3817, "2020-11-16": 0.3623, "2020-12-02": 0.3423, "2020-12-18": 0.3357, "2021-01-01": 0.3383, "2021-01-17": 0.3636, "2021-02-02": 0.3704, "2021-02-18": 0.3975, "2021-03-06": 0.379, "2021-03-22": 0.3692, "2021-04-07": 0.343, "2021-04-23": 0.3151, "2021-05-09": 0.2758, "2021-05-25": 0.382, "2021-06-10": 0.3239, "2021-06-26": 0.3929, "2021-07-12": 0.2872, "2021-07-28": 0.2077, "2021-08-13": 0.4752, "2021-08-29": 0.3973, "2021-09-14": 0.4249, "2021-09-30": 0.6024, "2021-10-16": 0.5199, "2021-11-01": 0.4052, "2021-11-17": 0.392, "2021-12-03": 0.364, "2021-12-19": 0.3484, "2022-01-01": 0.3774, "2022-01-17": 0.3547, "2022-02-02": 0.3424, "2022-02-18": 0.3364, "2022-03-06": 0.3652, "2022-03-22": 0.3512, "2022-04-07": 0.3501, "2022-04-23": 0.3293, "2022-05-09": 0.2757, "2022-05-25": 0.2602, "2022-06-10": 0.2672, "2022-06-26": 0.2453, "2022-07-12": 0.1802, "2022-07-28": 0.3711, "2022-08-13": 0.5843, "2022-08-29": 0.5887, "2022-09-14": 0.5644, "2022-09-30": 0.5629, "2022-10-16": 0.4718, "2022-11-01": 0.4213, "2022-11-17": 0.3811, "2022-12-03": 0.3642, "2022-12-19": 0.359, "2023-01-01": 0.349, "2023-01-17": 0.3463, "2023-02-02": 0.3522, "2023-02-18": 0.352, "2023-03-06": 0.3809, "2023-03-22": 0.3527, "2023-04-07": 0.3173, "2023-04-23": 0.3117, "2023-05-09": 0.3051, "2023-05-25": 0.3081, "2023-06-10": 0.3358, "2023-06-26": 0.3986, "2023-07-12": 0.251, "2023-07-28": 0.1137, "2023-08-13": 0.4085, "2023-08-29": 0.5087, "2023-09-14": 0.552, "2023-09-30": 0.5681, "2023-10-16": 0.446, "2023-11-01": 0.3846, "2023-11-17": 0.3614, "2023-12-03": 0.4012, "2023-12-19": 0.3699, "2024-01-01": 0.3788, "2024-01-17": 0.368, "2024-02-02": 0.3728, "2024-02-18": 0.3722, "2024-03-05": 0.3616, "2024-03-21": 0.3399, "2024-04-06": 0.3204, "2024-04-22": 0.3327, "2024-05-08": 0.2957, "2024-05-24": 0.2708, "2024-06-09": 0.2932, "2024-06-25": 0.273, "2024-07-11": 0.3789, "2024-07-27": 0.0895, "2024-08-12": 0.5148, "2024-08-28": 0.5879, "2024-09-13": 0.5875, "2024-09-29": 0.5687, "2024-10-15": 0.5227, "2024-10-31": 0.4301, "2024-11-16": 0.4026, "2024-12-02": 0.3722, "2024-12-18": 0.3585, "2025-01-01": 0.3788, "2025-01-17": 0.3559, "2025-02-02": 0.3745, "2025-02-18": 0.3588, "2025-03-06": 0.378, "2025-03-22": 0.3505, "2025-04-07": 0.3419, "2025-04-23": 0.3337, "2025-05-09": 0.3846, "2025-05-25": 0.3916, "2025-06-10": 0.3746, "2025-06-26": 0.2351, "2025-07-12": 0.3143, "2025-07-28": 0.4494, "2025-08-13": 0.189, "2025-08-29": 0.5752, "2025-09-14": 0.5931, "2025-09-30": 0.4848, "2025-10-16": 0.5151, "2025-11-01": 0.4802, "2025-11-17": 0.4519, "2025-12-03": 0.4092, "2025-12-19": 0.4078, "2026-01-01": 0.3763, "2026-01-17": 0.3696, "2026-02-02": 0.351, "2026-02-18": 0.4222}, "forecast": {"2026-02-19": 0.4096, "2026-02-20": 0.3992, "2026-02-21": 0.411, "2026-02-22": 0.4047, "2026-02-23": 0.4063, "2026-02-24": 0.4068, "2026-02-25": 0.406, "2026-02-26": 0.4065, "2026-02-27": 0.4063, "2026-02-28": 0.4063, "2026-03-01": 0.4064, "2026-03-02": 0.4063, "2026-03-03": 0.4063, "2026-03-04": 0.4063, "2026-03-05": 0.4063, "2026-03-06": 0.4063, "2026-03-07": 0.4063, "2026-03-08": 0.4063, "2026-03-09": 0.4063, "2026-03-10": 0.4063, "2026-03-11": 0.4063, "2026-03-12": 0.4063, "2026-03-13": 0.4063, "2026-03-14": 0.4063, "2026-03-15": 0.4063, "2026-03-16": 0.4063, "2026-03-17": 0.4063, "2026-03-18": 0.4063, "2026-03-19": 0.4063, "2026-03-20": 0.4063}, "trend_direction": "decreasing", "model": "ARIMA(2,1,1)", "forecast_days": 30}, "hotspots": {"parameter": "NDVI", "city": "ahmedabad", "hotspots": [{"cluster_id": 0, "center_lat": 23.0235, "center_lng": 72.5504, "avg_value": 0.2314, "num_points": 34116, "severity": "critical", "parameter": "NDVI", "radius_km": 2.2}], "total_points": 136462, "hot_points": 34116, "cluster_count": 1, "threshold": 0.4592}}, "NO2": {"anomalies": {"parameter": "NO2", "city": "ahmedabad", "anomalies": [{"date": "2021-01-01", "lat": 22.91, "lng": 72.55, "value": 0.0001, "severity": "high", "anomaly_score": -0.1605, "deviation": 1.79, "direction": "above", "description": "Pollution spike \u2014 NO2 concentration significantly elevated. Likely industrial emission event, traffic surge, or atmospheric inversion trapping pollutants.", "parameter": "NO2"}, {"date": "2021-09-01", "lat": 22.9, "lng": 72.4, "value": 0.0, "severity": "moderate", "anomaly_score": -0.0752, "deviation": 1.6, "direction": "below", "description": "Slightly below-normal NO2. Minor air quality improvement detected.", "parameter": "NO2"}, {"date": "2021-03-01", "lat": 23.05, "lng": 72.55, "value": 0.0001, "severity": "moderate", "anomaly_score": -0.0595, "deviation": 1.25, "direction": "above", "description": "Above-average NO2 levels. Gradual air quality degradation \u2014 check industrial and traffic sources.", "parameter": "NO2"}, {"date": "2023-08-01", "lat": 22.9, "lng": 72.4, "value": 0.0, "severity": "moderate", "anomaly_score": -0.0023, "deviation": 1.47, "direction": "below", "description": "Slightly below-normal NO2. Minor air quality improvement detected.", "parameter": "NO2"}, {"date": "2025-08-01", "lat": 22.9, "lng": 72.4, "value": 0.0, "severity": "moderate", "anomaly_score": -0.0023, "deviation": 1.47, "direction": "below", "description": "Slightly below-normal NO2. Minor air quality improvement detected.", "parameter": "NO2"}], "total_points": 72075, "dates_analyzed": 75, "anomaly_count": 5, "contamination": 0.08}, "trends": {"parameter": "NO2", "city": "ahmedabad", "historical": {"2020-01-01": 0.0001, "2020-02-01": 0.0001, "2020-03-01": 0.0001, "2020-04-01": 0.0, "2020-05-01": 0.0, "2020-06-01": 0.0, "2020-07-01": 0.0, "2020-08-01": 0.0, "2020-09-01": 0.0, "2020-10-01": 0.0001, "2020-11-01": 0.0001, "2020-12-01": 0.0001, "2021-01-01": 0.0001, "2021-02-01": 0.0001, "2021-03-01": 0.0001, "2021-04-01": 0.0001, "2021-05-01": 0.0, "2021-06-01": 0.0, "2021-07-01": 0.0, "2021-08-01": 0.0, "2021-09-01": 0.0, "2021-10-01": 0.0001, "2021-11-01": 0.0001, "2021-12-01": 0.0001, "2022-01-01": 0.0001, "2022-02-01": 0.0001, "2022-03-01": 0.0001, "2022-04-01": 0.0001, "2022-05-01": 0.0, "2022-06-01": 0.0, "2022-07-01": 0.0, "2022-08-01": 0.0, "2022-09-01": 0.0, "2022-10-01": 0.0001, "2022-11-01": 0.0001, "2022-12-01": 0.0001, "2023-01-01": 0.0001, "2023-02-01": 0.0001, "2023-03-01": 0.0001, "2023-04-01": 0.0001, "2023-05-01": 0.0001, "2023-06-01": 0.0, "2023-07-01": 0.0, "2023-08-01": 0.0, "2023-09-01": 0.0001, "2023-10-01": 0.0001, "2023-11-01": 0.0001, "2023-12-01": 0.0001, "2024-01-01": 0.0001, "2024-02-01": 0.0001, "2024-03-01": 0.0001, "2024-04-01": 0.0001, "2024-05-01": 0.0001, "2024-06-01": 0.0001, "2024-07-01": 0.0, "2024-08-01": 0.0, "2024-09-01": 0.0, "2024-10-01": 0.0001, "2024-11-01": 0.0001, "2024-12-01": 0.0001, "2025-01-01": 0.0001, "2025-02-01": 0.0001, "2025-03-01": 0.0001, "2025-04-01": 0.0001, "2025-05-01": 0.0, "2025-06-01": 0.0001, "2025-07-01": 0.0, "2025-08-01": 0.0, "2025-09-01": 0.0, "2025-10-01": 0.0001, "2025-11-01": 0.0001, "2025-12-01": 0.0001, "2026-01-01": 0.0001, "2026-02-01": 0.0001, "2026-03-01": 0.0001}, "forecast": {"2026-03-02": 0.0001, "2026-03-03": 0.0001, "2026-03-04": 0.0001, "2026-03-05": 0.0001, "2026-03-06": 0.0001, "2026-03-07": 0.0001, "2026-03-08": 0.0001, "2026-03-09": 0.0001, "2026-03-10": 0.0001, "2026-03-11": 0.0001, "2026-03-12": 0.0001, "2026-03-13": 0.0001, "2026-03-14": 0.0001, "2026-03-15": 0.0001, "2026-03-16": 0.0001, "2026-03-17": 0.0001, "2026-03-18": 0.0001, "2026-03-19": 0.0001, "2026-03-20": 0.0001, "2026-03-21": 0.0001, "2026-03-22": 0.0001, "2026-03-23": 0.0001, "2026-03-24": 0.0001, "2026-03-25": 0.0001, "2026-03-26": 0.0001, "2026-03-27": 0.0001, "2026-03-28": 0.0001, "2026-03-29": 0.0001, "2026-03-30": 0.0001, "2026-03-31": 0.0001}, "trend_direction": "decreasing", "model": "ARIMA(2,1,1)", "forecast_days": 30}, "hotspots": {"parameter": "NO2", "city": "ahmedabad", "hotspots": [{"cluster_id": 0, "center_lat": 23.0409, "center_lng": 72.5617, "avg_value": 0.0001, "num_points": 33982, "severity": "critical", "parameter": "NO2", "radius_km": 2.2}], "total_points": 72075, "hot_points": 33982, "cluster_count": 1, "threshold": 0.0001}}, "SOIL_MOISTURE": {"anomalies": {"parameter": "SOIL_MOISTURE", "city": "ahmedabad", "anomalies": [{"date": "2020-01-27", "lat": 22.91, "lng": 72.55, "value": 0.2567, "severity": "moderate", "anomaly_score": -0.1465, "deviation": 1.81, "direction": "above", "description": "Above-average soil moisture. Favorable for agriculture but monitor for waterlogging.", "parameter": "SOIL_MOISTURE"}, {"date": "2020-02-04", "lat": 22.91, "lng": 72.55, "value": 0.2487, "severity": "moderate", "anomaly_score": -0.0738, "deviation": 1.6, "direction": "above", "description": "Above-average soil moisture. Favorable for agriculture but monitor for waterlogging.", "parameter": "SOIL_MOISTURE"}, {"date": "2020-05-29", "lat": 23.19, "lng": 72.69, "value": 0.1241, "severity": "moderate", "anomaly_score": -0.0647, "deviation": 1.68, "direction": "below", "description": "Slightly dry conditions. Early drought indicator \u2014 recommend water conservation measures.", "parameter": "SOIL_MOISTURE"}, {"date": "2020-05-18", "lat": 22.91, "lng": 72.41, "value": 0.1249, "severity": "moderate", "anomaly_score": -0.0393, "deviation": 1.66, "direction": "below", "description": "Slightly dry conditions. Early drought indicator \u2014 recommend water conservation measures.", "parameter": "SOIL_MOISTURE"}, {"date": "2020-05-23", "lat": 22.91, "lng": 72.41, "value": 0.1295, "severity": "moderate", "anomaly_score": -0.0064, "deviation": 1.54, "direction": "below", "description": "Slightly dry conditions. Early drought indicator \u2014 recommend water conservation measures.", "parameter": "SOIL_MOISTURE"}], "total_points": 52855, "dates_analyzed": 55, "anomaly_count": 5, "contamination": 0.08}, "trends": {"parameter": "SOIL_MOISTURE", "city": "ahmedabad", "historical": {"2020-01-03": 0.2324, "2020-01-06": 0.21, "2020-01-08": 0.2227, "2020-01-11": 0.2073, "2020-01-14": 0.2348, "2020-01-16": 0.2155, "2020-01-19": 0.2308, "2020-01-24": 0.2393, "2020-01-27": 0.2567, "2020-01-30": 0.2323, "2020-02-01": 0.2326, "2020-02-04": 0.2487, "2020-02-07": 0.2233, "2020-02-09": 0.2229, "2020-02-12": 0.2243, "2020-02-15": 0.2387, "2020-02-17": 0.2097, "2020-02-20": 0.2354, "2020-02-23": 0.2105, "2020-02-25": 0.2242, "2020-02-28": 0.2174, "2020-03-02": 0.196, "2020-03-04": 0.2194, "2020-03-07": 0.2294, "2020-03-10": 0.1834, "2020-03-12": 0.2033, "2020-03-15": 0.1893, "2020-03-18": 0.172, "2020-03-20": 0.1807, "2020-03-23": 0.1708, "2020-03-26": 0.175, "2020-03-28": 0.2047, "2020-03-31": 0.1756, "2020-04-03": 0.1709, "2020-04-05": 0.1681, "2020-04-08": 0.1701, "2020-04-11": 0.1636, "2020-04-13": 0.1681, "2020-04-16": 0.166, "2020-04-19": 0.1597, "2020-04-21": 0.156, "2020-04-24": 0.1535, "2020-04-27": 0.1455, "2020-04-29": 0.1519, "2020-05-02": 0.1476, "2020-05-05": 0.1429, "2020-05-07": 0.1515, "2020-05-10": 0.1341, "2020-05-13": 0.1324, "2020-05-15": 0.1346, "2020-05-18": 0.1249, "2020-05-21": 0.1362, "2020-05-23": 0.1295, "2020-05-26": 0.133, "2020-05-29": 0.1241}, "forecast": {"2020-05-30": 0.1292, "2020-05-31": 0.1282, "2020-06-01": 0.1273, "2020-06-02": 0.1284, "2020-06-03": 0.1278, "2020-06-04": 0.1279, "2020-06-05": 0.128, "2020-06-06": 0.1279, "2020-06-07": 0.1279, "2020-06-08": 0.128, "2020-06-09": 0.1279, "2020-06-10": 0.1279, "2020-06-11": 0.1279, "2020-06-12": 0.1279, "2020-06-13": 0.1279, "2020-06-14": 0.1279, "2020-06-15": 0.1279, "2020-06-16": 0.1279, "2020-06-17": 0.1279, "2020-06-18": 0.1279, "2020-06-19": 0.1279, "2020-06-20": 0.1279, "2020-06-21": 0.1279, "2020-06-22": 0.1279, "2020-06-23": 0.1279, "2020-06-24": 0.1279, "2020-06-25": 0.1279, "2020-06-26": 0.1279, "2020-06-27": 0.1279, "2020-06-28": 0.1279}, "trend_direction": "increasing", "model": "ARIMA(2,1,1)", "forecast_days": 30}, "hotspots": {"parameter": "SOIL_MOISTURE", "city": "ahmedabad", "hotspots": [{"cluster_id": 0, "center_lat": 23.0072, "center_lng": 72.5345, "avg_value": 0.2416, "num_points": 13214, "severity": "critical", "parameter": "SOIL_MOISTURE", "radius_km": 2.2}], "total_points": 52855, "hot_points": 13214, "cluster_count": 1, "threshold": 0.2186}}}